gpt_pdf_organizer/__init__.py
gpt_pdf_organizer/gpt_pdf_organizer.py
gpt_pdf_organizer/app/__init__.py
gpt_pdf_organizer/app/application.py
gpt_pdf_organizer/app/exception.py
gpt_pdf_organizer/domain/__init__.py
gpt_pdf_organizer/domain/attribute.py
gpt_pdf_organizer/domain/prompt_builder.py
gpt_pdf_organizer/infrastructure/__init__.py
gpt_pdf_organizer/infrastructure/gpt_prompt_querier.py
gpt_pdf_organizer/service/__init__.py
gpt_pdf_organizer/service/prompt_querier.py
gpt_pdf_organizer/utils/__init__.py
gpt_pdf_organizer/utils/config.py
gpt_pdf_organizer/utils/file.py
gpt_pdf_organizer/utils/pdf.py
gpt_pdf_organizer/utils/tokenizer.py
gpt_pdf_organizer-0.1.4.dist-info/METADATA
gpt_pdf_organizer-0.1.4.dist-info/WHEEL
gpt_pdf_organizer-0.1.4.dist-info/entry_points.txt
gpt_pdf_organizer-0.1.4.dist-info/top_level.txt
gpt_pdf_organizer-0.1.4.dist-info/RECORD
