Metadata-Version: 2.1
Name: gpt-pdf-organizer
Version: 0.1.4
Summary: UNKNOWN
Home-page: UNKNOWN
License: UNKNOWN
Platform: UNKNOWN
Requires-Dist: pyyaml ==6.0.1
Requires-Dist: openai ==1.9.0
Requires-Dist: tiktoken ==0.5.2
Requires-Dist: pdfplumber ==0.10.3
Requires-Dist: rich ==13.7.0
